pre_script.pth
pre_script/__init__.py
pre_script-0.1.2.dist-info/LICENSE
pre_script-0.1.2.dist-info/METADATA
pre_script-0.1.2.dist-info/WHEEL
pre_script-0.1.2.dist-info/RECORD
