Metadata-Version: 2.1
Name: pre-script
Version: 0.1.2
Summary: Util for executing a custom script before running any python application without modifying the last one
Home-page: https://github.com/gtors/pre-script
License: MIT
Author: Andrey Torsunov
Author-email: andrey.torsunov@gmail.com
Requires-Python: >=3.7,<4.0
Classifier: Development Status :: 5 - Production/Stable
Classifier: License :: OSI Approved :: MIT License
Classifier: Programming Language :: Python :: 3
Classifier: Programming Language :: Python :: 3.7
Classifier: Programming Language :: Python :: 3.8
Classifier: Programming Language :: Python :: 3.9
Classifier: Programming Language :: Python :: 3.10
Classifier: Programming Language :: Python :: 3.11
Project-URL: Changelog, https://github.com/gtors/pre-script/releases
Project-URL: Repository, https://github.com/gtors/pre-script
